foamfile/__init__.py
foamfile/foamfile.py
foamfile-0.11.dist-info/LICENSE.txt
foamfile-0.11.dist-info/METADATA
foamfile-0.11.dist-info/WHEEL
foamfile-0.11.dist-info/top_level.txt
foamfile-0.11.dist-info/RECORD
