Metadata-Version: 2.1
Name: foamfile
Version: 0.11
Summary: OpenFOAM config file parser
Home-page: https://github.com/napyk/foamfile
Author: Nikolas Pfister
Author-email: pfister.nikolas@gmail.com
License: MIT
Platform: UNKNOWN
Requires-Dist: pyparsing (==2.4.2)
